langwhat/__init__.py
langwhat/__main__.py
langwhat/cli.py
langwhat/config.py
langwhat/langwhat.py
langwhat/llm.py
langwhat/tests/data.py
langwhat/utils.py
langwhat-2.0.3.dist-info/LICENSE
langwhat-2.0.3.dist-info/METADATA
langwhat-2.0.3.dist-info/WHEEL
langwhat-2.0.3.dist-info/entry_points.txt
langwhat-2.0.3.dist-info/RECORD
