Metadata-Version: 2.1
Name: langwhat
Version: 2.0.3
Summary: What is it? pyWhat but with LLMs
Home-page: https://github.com/tddschn/langwhat
License: MIT
Keywords: LLM
Author: Teddy Xinyuan Chen
Author-email: 45612704+tddschn@users.noreply.github.com
Requires-Python: >=3.11,<4.0
Classifier: License :: OSI Approved :: MIT License
Classifier: Programming Language :: Python :: 3
Classifier: Programming Language :: Python :: 3.11
Classifier: Topic :: Utilities
Requires-Dist: edgegpt (>=0.0.55,<0.0.56)
Requires-Dist: langchain (>=0.0.105,<0.0.106)
Requires-Dist: openai (>=0.27.1,<0.28.0)
Requires-Dist: rich (>=13.3.2,<14.0.0)
Project-URL: Bug Tracker, https://github.com/tddschn/langwhat/issues
Project-URL: Repository, https://github.com/tddschn/langwhat
